{
    "clientes": [
        {
            "DNI": "43456832",
            "group": "gold",
            "birthdate": "21/05/2001"
        },
        {
            "DNI": "12345678",
            "group": "platinum",
            "birthdate": "15/08/1995"
        },
        {
            "DNI": "87654321",
            "group": "black",
            "birthdate": "30/12/1980"
        },
        {
            "DNI": "11223344",
            "group": "gold",
            "birthdate": "10/03/1990"
        },
        {
            "DNI": "55667788",
            "group": "platinum",
            "birthdate": "25/07/1985"
        }
    ]
}